openapi_agent_benchmark/__init__.py
openapi_agent_benchmark/applications/__init__.py
openapi_agent_benchmark/applications/base.py
openapi_agent_benchmark/authentications/__init__.py
openapi_agent_benchmark/authentications/factory.py
openapi_agent_benchmark/authentications/provider.py
openapi_agent_benchmark/authentications/providers/__init__.py
openapi_agent_benchmark/authentications/providers/bookstack.py
openapi_agent_benchmark/authentications/providers/coolify.py
openapi_agent_benchmark/authentications/providers/fireflyiii.py
openapi_agent_benchmark/authentications/providers/invoiceninja.py
openapi_agent_benchmark/authentications/providers/kimai.py
openapi_agent_benchmark/authentications/providers/koel.py
openapi_agent_benchmark/authentications/providers/partdbserver.py
openapi_agent_benchmark/evaluations/__main__.py
openapi_agent_benchmark/evaluations/evaluator.py
openapi_agent_benchmark/evaluations/runner.py
openapi_agent_benchmark/evaluations/tracer.py
openapi_agent_benchmark/evaluations/models/openapi_agent.py
openapi_agent_benchmark/evaluations/models/openapi_agent_result.py
openapi_agent_benchmark/evaluations/models/openapi_agent_token_summary.py
openapi_agent_benchmark/evaluations/models/openapi_type.py
openapi_agent_benchmark/evaluations/utils/multipass.py
openapi_agent_benchmark/evaluations/utils/validator.py
openapi_agent_benchmark/evaluations/utils/waiter.py
openapi_agent_benchmark/generators/__main__.py
openapi_agent_benchmark/generators/models.py
openapi_agent_benchmark/tasks/coolify/task_01/verifier.py
openapi_agent_benchmark/tasks/coolify/task_02/verifier.py
openapi_agent_benchmark/tasks/coolify/task_03/verifier.py
openapi_agent_benchmark/tasks/coolify/task_04/verifier.py
openapi_agent_benchmark/tasks/coolify/task_05/verifier.py
openapi_agent_benchmark/tasks/coolify/task_06/verifier.py
openapi_agent_benchmark/tasks/coolify/task_07/verifier.py
openapi_agent_benchmark/tasks/coolify/task_08/verifier.py
openapi_agent_benchmark-0.1.5.dist-info/METADATA
openapi_agent_benchmark-0.1.5.dist-info/WHEEL
openapi_agent_benchmark-0.1.5.dist-info/top_level.txt
openapi_agent_benchmark-0.1.5.dist-info/RECORD
