Metadata-Version: 2.4
Name: openapi-agent-benchmark
Version: 0.1.5
Summary: Add your description here
Requires-Python: >=3.12
Requires-Dist: bs4>=0.0.2
Requires-Dist: dotenv>=0.9.9
Requires-Dist: instructor>=1.11.3
Requires-Dist: jinja2>=3.1.6
Requires-Dist: langchain-community>=0.3.29
Requires-Dist: langchain-deepseek>=0.1.4
Requires-Dist: openai>=1.109.0
Requires-Dist: pydantic>=2.11.9
Requires-Dist: requests>=2.32.5
Requires-Dist: rich>=14.1.0
Requires-Dist: structlog>=25.4.0
Requires-Dist: typer>=0.19.2
